tgju/__init__.py
tgju/currency_service.py
tgju-0.0.1b0.dist-info/METADATA
tgju-0.0.1b0.dist-info/WHEEL
tgju-0.0.1b0.dist-info/licenses/LICENSE
tgju-0.0.1b0.dist-info/RECORD
