Metadata-Version: 2.4
Name: tgju
Version: 0.0.1b0
Summary: A Python client for fetching live currency and asset prices from the TGJU API.
Project-URL: Source Code, https://github.com/AmirHosseinMoloudi/tgju-org-exchange-rate-scraper
Project-URL: Bug Tracker, https://github.com/AmirHosseinMoloudi/tgju-org-exchange-rate-scraper/issues
Author-email: AmirHosseinMoloudi <ahmoloudi786@gmail.com>
License: MIT License
License-File: LICENSE
Keywords: api,currency,exchange rates,finance,iran,rial,tgju
Classifier: Development Status :: 4 - Beta
Classifier: Intended Audience :: Developers
Classifier: License :: OSI Approved :: MIT License
Classifier: Operating System :: OS Independent
Classifier: Programming Language :: Python :: 3
Classifier: Programming Language :: Python :: 3.8
Classifier: Programming Language :: Python :: 3.9
Classifier: Programming Language :: Python :: 3.10
Classifier: Programming Language :: Python :: 3.11
Classifier: Programming Language :: Python :: 3.12
Classifier: Topic :: Office/Business :: Financial
Classifier: Topic :: Software Development :: Libraries :: Python Modules
Classifier: Typing :: Typed
Requires-Python: >=3.8
Requires-Dist: httpx>=0.20
Provides-Extra: test
Requires-Dist: pytest-asyncio>=0.18; extra == 'test'
Requires-Dist: pytest>=7.0; extra == 'test'
Requires-Dist: respx>=0.20; extra == 'test'
